pysb/pkpd/__init__.py
pysb/pkpd/macros.py
pysb/pkpd/standard.py
pysb/pkpd/util.py
pysb/pkpd/models/__init__.py
pysb/pkpd/models/three_compartment_emax.py
pysb/pkpd/models/two_compartment_emax.py
pysb/pkpd/pk_models/__init__.py
pysb/pkpd/pk_models/three_compartment.py
pysb/pkpd/pk_models/two_compartment.py
pysb_pkpd-0.5.3.dist-info/licenses/LICENSE
pysb_pkpd-0.5.3.dist-info/METADATA
pysb_pkpd-0.5.3.dist-info/WHEEL
pysb_pkpd-0.5.3.dist-info/top_level.txt
pysb_pkpd-0.5.3.dist-info/RECORD
